helmdt.py
objects/__init__.py
objects/profiles.py
utils/__init__.py
utils/azure.py
utils/colorc.py
utils/depcheck.py
utils/docker.py
utils/helm.py
utils/run.py
helmdt-0.6.3.dist-info/LICENSE
helmdt-0.6.3.dist-info/METADATA
helmdt-0.6.3.dist-info/WHEEL
helmdt-0.6.3.dist-info/entry_points.txt
helmdt-0.6.3.dist-info/top_level.txt
helmdt-0.6.3.dist-info/RECORD
