Metadata-Version: 2.1
Name: helmdt
Version: 0.6.3
Summary: A HELM Deployment toolkit
Home-page: https://github.com/toshiya14/helmdt
Author: Akaishi Toshiya
Author-email: Toshiya14@live.jp
License: MIT
Classifier: Programming Language :: Python :: 3.9
Classifier: Operating System :: OS Independent
Requires-Python: >=3.9
License-File: LICENSE
Requires-Dist: click
Requires-Dist: inquirerpy
Requires-Dist: pyyaml
Requires-Dist: reprint
